[
  {
    "id": 1,
    "title": "GOT",
    "image": "localhost/images/small1.png"
  },
  {
    "id": 2,
    "title": "Loki",
    "image": "localhost/images/small2.png"
  },
  {
    "id": 3,
    "title": "Fatherhood",
    "image": "localhost/images/small3.png"
  },
  {
    "id": 4,
    "title": "GOT",
    "image": "localhost/images/small4.png"
  },
  {
    "id": 5,
    "title": "FLash",
    "image": "localhost/images/small5.png"
  },
  {
    "id": 6,
    "title": "Arrow",
    "image": "localhost/images/small1.png"
  }
]
